{"@attributes":{"Name":"Horse Racing","PageTitle":"Filtered applied. EventID: 117722917","TimeStamp":"10\/07\/22 18:27:01"},"Event":{"@attributes":{"Name":"Grand National","ID":"117722917","OffTime":"15\/04\/23 17:15:00","EventComment":"","Going":"","RaceType":"","RaceDistance":"","PlaceCount":"4","PlaceOdds":"1\/4","PGID":"117722917"},"Market":{"@attributes":{"Name":"Win And Each Way","ID":"1744","FID":"117722917"},"Participant":[{"@attributes":{"Name":"Minella Times","Odds":"33\/1","OddsDecimal":"34.00","OddsAmerican":"3300","RaceOffOdds":"","SaddleCloth":"0","ID":"875715942","LastUpdated":"22\/06\/22 15:26:38","AVG":"36205027ACE829B18F7DA865A1F0CA0FD220E177"}},{"@attributes":{"Name":"Longhouse Poet","Odds":"33\/1","OddsDecimal":"34.00","OddsAmerican":"3300","RaceOffOdds":"","SaddleCloth":"0","ID":"875715949","LastUpdated":"22\/06\/22 15:26:38","AVG":"700CB50CFEBFA8FAEB0E151D05AA0EF38A0E8466"}},{"@attributes":{"Name":"Win My Wings","Odds":"33\/1","OddsDecimal":"34.00","OddsAmerican":"3300","RaceOffOdds":"","SaddleCloth":"0","ID":"875715957","LastUpdated":"22\/06\/22 15:26:38","AVG":"D7183FE210938982CDF1DDAC5523DE4026621274"}},{"@attributes":{"Name":"Kitty's Light","Odds":"25\/1","OddsDecimal":"26.00","OddsAmerican":"2500","RaceOffOdds":"","SaddleCloth":"0","ID":"875715965","LastUpdated":"22\/06\/22 15:26:38","AVG":"EBC201DFF300ED6B7762CC6D446FCD3789076ACE"}},{"@attributes":{"Name":"Fiddlerontheroof","Odds":"33\/1","OddsDecimal":"34.00","OddsAmerican":"3300","RaceOffOdds":"","SaddleCloth":"0","ID":"875715973","LastUpdated":"22\/06\/22 15:26:38","AVG":"383FB4652A2FC9B5B17CE1721BB448FD5B1AF726"}},{"@attributes":{"Name":"Delta Work","Odds":"25\/1","OddsDecimal":"26.00","OddsAmerican":"2500","RaceOffOdds":"","SaddleCloth":"0","ID":"875715991","LastUpdated":"22\/06\/22 15:26:38","AVG":"27D9B918883E6BD22D0D69130756BFCB24E64F65"}},{"@attributes":{"Name":"Run Wild Fred","Odds":"33\/1","OddsDecimal":"34.00","OddsAmerican":"3300","RaceOffOdds":"","SaddleCloth":"0","ID":"875716101","LastUpdated":"22\/06\/22 15:26:38","AVG":"BACB889C8C30F9F5A67EF2D4B5B7DD2D05261D94"}},{"@attributes":{"Name":"Enjoy D'allen","Odds":"40\/1","OddsDecimal":"41.00","OddsAmerican":"4000","RaceOffOdds":"","SaddleCloth":"0","ID":"875716158","LastUpdated":"22\/06\/22 15:26:38","AVG":"670590DDB75A74289DAD1B79368FD89C4BD89467"}},{"@attributes":{"Name":"Noble Yeats","Odds":"16\/1","OddsDecimal":"17.00","OddsAmerican":"1600","RaceOffOdds":"","SaddleCloth":"0","ID":"876401790","LastUpdated":"22\/06\/22 15:26:38","AVG":"1FC152B2398C5C9C4E3FDC8E92575D77E651F618"}},{"@attributes":{"Name":"Any Second Now","Odds":"20\/1","OddsDecimal":"21.00","OddsAmerican":"2000","RaceOffOdds":"","SaddleCloth":"0","ID":"876401791","LastUpdated":"22\/06\/22 15:26:38","AVG":"BC68DCE63A7363519857BB782EBF49D98981CF37"}},{"@attributes":{"Name":"Santini","Odds":"33\/1","OddsDecimal":"34.00","OddsAmerican":"3300","RaceOffOdds":"","SaddleCloth":"0","ID":"876401792","LastUpdated":"22\/06\/22 15:26:38","AVG":"CCD86E42817328CEDF7EDB417A827F888E15754F"}},{"@attributes":{"Name":"Gericault Roque","Odds":"40\/1","OddsDecimal":"41.00","OddsAmerican":"4000","RaceOffOdds":"","SaddleCloth":"0","ID":"891714139","LastUpdated":"22\/06\/22 15:26:38","AVG":"C9296E6A0E64B53D3497EF52A32A4A7AC7398AD7"}},{"@attributes":{"Name":"Sam Brown","Odds":"50\/1","OddsDecimal":"51.00","OddsAmerican":"5000","RaceOffOdds":"","SaddleCloth":"0","ID":"891714140","LastUpdated":"22\/06\/22 15:26:38","AVG":"CA4141FCD4895CEE4E73903C0EF914DD9699BC95"}},{"@attributes":{"Name":"Coko Beach","Odds":"100\/1","OddsDecimal":"101.00","OddsAmerican":"10000","RaceOffOdds":"","SaddleCloth":"0","ID":"891714141","LastUpdated":"22\/06\/22 15:26:38","AVG":"21BFB3E5AA45970B99F316D7A15296B15AB95FC8"}},{"@attributes":{"Name":"Stattler","Odds":"25\/1","OddsDecimal":"26.00","OddsAmerican":"2500","RaceOffOdds":"","SaddleCloth":"0","ID":"891714142","LastUpdated":"22\/06\/22 15:26:38","AVG":"A1DC605F6A66600CC1CAFAE73FE081D1D4D4A4A8"}},{"@attributes":{"Name":"Commodore","Odds":"66\/1","OddsDecimal":"67.00","OddsAmerican":"6600","RaceOffOdds":"","SaddleCloth":"0","ID":"891714145","LastUpdated":"22\/06\/22 15:26:38","AVG":"D2794BDF56EF1A43C5833228E5273F54415DDC57"}},{"@attributes":{"Name":"Corach Rambler","Odds":"25\/1","OddsDecimal":"26.00","OddsAmerican":"2500","RaceOffOdds":"","SaddleCloth":"0","ID":"891714148","LastUpdated":"22\/06\/22 15:26:38","AVG":"CEE5C3ED76F9083220D7713D0A508BE33615056B"}},{"@attributes":{"Name":"Secret Reprieve","Odds":"33\/1","OddsDecimal":"34.00","OddsAmerican":"3300","RaceOffOdds":"","SaddleCloth":"0","ID":"891714149","LastUpdated":"22\/06\/22 15:26:38","AVG":"905C3152AE81020E9DCE9ACE7D56772998815891"}},{"@attributes":{"Name":"Snow Leopardess","Odds":"40\/1","OddsDecimal":"41.00","OddsAmerican":"4000","RaceOffOdds":"","SaddleCloth":"0","ID":"901327955","LastUpdated":"22\/06\/22 15:26:38","AVG":"57E8DF6C5DE32EFB480AF87FFED0638A22E56015"}},{"@attributes":{"Name":"Freewheelin Dylan","Odds":"66\/1","OddsDecimal":"67.00","OddsAmerican":"6600","RaceOffOdds":"","SaddleCloth":"0","ID":"902463621","LastUpdated":"08\/07\/22 20:04:35","AVG":"8E7CDF2641BC99199867B37DFCE1E23BDFC7D84F"}},{"@attributes":{"Name":"Iwilldoit","Odds":"33\/1","OddsDecimal":"34.00","OddsAmerican":"3300","RaceOffOdds":"","SaddleCloth":"0","ID":"906911340","LastUpdated":"22\/06\/22 15:26:39","AVG":"13228D68538679C5D2CF47E4276A1B56E1F0104E"}},{"@attributes":{"Name":"Topofthegame","Odds":"40\/1","OddsDecimal":"41.00","OddsAmerican":"4000","RaceOffOdds":"","SaddleCloth":"0","ID":"906911341","LastUpdated":"22\/06\/22 15:26:39","AVG":"B5823970CC425820ED9638A0BE65F3F228CB7B50"}},{"@attributes":{"Name":"Gaillard Du Mesnil","Odds":"50\/1","OddsDecimal":"51.00","OddsAmerican":"5000","RaceOffOdds":"","SaddleCloth":"0","ID":"912226663","LastUpdated":"22\/06\/22 15:26:39","AVG":"085C8ABCBA679AF9DA3B7DCD4BC3CCA8DB7A6786"}},{"@attributes":{"Name":"Mac Tottie","Odds":"33\/1","OddsDecimal":"34.00","OddsAmerican":"3300","RaceOffOdds":"","SaddleCloth":"0","ID":"915657646","LastUpdated":"22\/06\/22 15:26:39","AVG":"DEDCE5139236D3566C4EB395FB0670098DB7FD17"}},{"@attributes":{"Name":"Fortescue","Odds":"66\/1","OddsDecimal":"67.00","OddsAmerican":"6600","RaceOffOdds":"","SaddleCloth":"0","ID":"915657662","LastUpdated":"22\/06\/22 15:26:39","AVG":"BCC405B7D26CEE50D1EB7096C2A58232DF3C8313"}},{"@attributes":{"Name":"Domaine De L'isle","Odds":"150\/1","OddsDecimal":"151.00","OddsAmerican":"15000","RaceOffOdds":"","SaddleCloth":"0","ID":"915657668","LastUpdated":"22\/06\/22 15:26:39","AVG":"0B92137D6D5A2BE749360986F9FE0D91FFB49FBC"}},{"@attributes":{"Name":"Happygolucky","Odds":"33\/1","OddsDecimal":"34.00","OddsAmerican":"3300","RaceOffOdds":"","SaddleCloth":"0","ID":"915657669","LastUpdated":"22\/06\/22 15:26:39","AVG":"15C71749E1B08F63A13C0F9485E533167BAA8858"}},{"@attributes":{"Name":"Franco De Port","Odds":"33\/1","OddsDecimal":"34.00","OddsAmerican":"3300","RaceOffOdds":"","SaddleCloth":"0","ID":"915657670","LastUpdated":"22\/06\/22 15:26:39","AVG":"0BBBC3A95AA718EE05A0DC123249C0245E4BDC3E"}},{"@attributes":{"Name":"Lord Lariat","Odds":"50\/1","OddsDecimal":"51.00","OddsAmerican":"5000","RaceOffOdds":"","SaddleCloth":"0","ID":"921084080","LastUpdated":"22\/06\/22 15:26:39","AVG":"7EE0962910CFA8E4894546C239949895A3CD996A"}},{"@attributes":{"Name":"Fidux","Odds":"100\/1","OddsDecimal":"101.00","OddsAmerican":"10000","RaceOffOdds":"","SaddleCloth":"0","ID":"921089219","LastUpdated":"22\/06\/22 15:26:39","AVG":"D7349197CB5091432EDE267439995E541907C10C"}},{"@attributes":{"Name":"Early Doors","Odds":"66\/1","OddsDecimal":"67.00","OddsAmerican":"6600","RaceOffOdds":"","SaddleCloth":"0","ID":"921090602","LastUpdated":"30\/06\/22 18:14:52","AVG":"9076DAF4FD4E772D1C7CC173460B90295414BDEF"}},{"@attributes":{"Name":"Screaming Colours","Odds":"66\/1","OddsDecimal":"67.00","OddsAmerican":"6600","RaceOffOdds":"","SaddleCloth":"0","ID":"924563781","LastUpdated":"22\/06\/22 15:26:39","AVG":"5813BE9235DF76DF915276DF4C2FCC4D52C12438"}},{"@attributes":{"Name":"Aramax","Odds":"150\/1","OddsDecimal":"151.00","OddsAmerican":"15000","RaceOffOdds":"","SaddleCloth":"0","ID":"931755466","LastUpdated":"22\/06\/22 15:26:39","AVG":"33B4B5902AAEE0140BCD3AB1C785C540563F153F"}},{"@attributes":{"Name":"Hewick","Odds":"33\/1","OddsDecimal":"34.00","OddsAmerican":"3300","RaceOffOdds":"","SaddleCloth":"0","ID":"943995276","LastUpdated":"22\/06\/22 15:26:39","AVG":"E8B5949140412F5197814EAACA8B876176B7F7DA"}},{"@attributes":{"Name":"Musical Slave","Odds":"50\/1","OddsDecimal":"51.00","OddsAmerican":"5000","RaceOffOdds":"","SaddleCloth":"0","ID":"957161603","LastUpdated":"22\/06\/22 15:26:39","AVG":"A6F9B425F9ED60C963E3EA504D64532EB7C41A6C"}},{"@attributes":{"Name":"Galvin","Odds":"25\/1","OddsDecimal":"26.00","OddsAmerican":"2500","RaceOffOdds":"","SaddleCloth":"0","ID":"957993283","LastUpdated":"22\/06\/22 15:26:39","AVG":"413731A126FBF7011BD4EB0C93FB533B15359D92"}},{"@attributes":{"Name":"Lifetime Ambition","Odds":"33\/1","OddsDecimal":"34.00","OddsAmerican":"3300","RaceOffOdds":"","SaddleCloth":"0","ID":"971799307","LastUpdated":"22\/06\/22 15:26:39","AVG":"8D7028F185231C5A8EECB963F4A3BE692E41F2CC"}},{"@attributes":{"Name":"The Galloping Bear","Odds":"40\/1","OddsDecimal":"41.00","OddsAmerican":"4000","RaceOffOdds":"","SaddleCloth":"0","ID":"1195406097","LastUpdated":"20\/06\/22 20:26:15","AVG":"3FAD5FF0786D7FD18F16AB8C41FE76CD11A8BB36"}},{"@attributes":{"Name":"Le Milos","Odds":"100\/1","OddsDecimal":"101.00","OddsAmerican":"10000","RaceOffOdds":"","SaddleCloth":"0","ID":"1244233313","LastUpdated":"02\/07\/22 13:36:47","AVG":"30201AFAC43588DD9DE6CBA5EEFD2C23CD30468C"}}]}}}