{"@attributes":{"Name":"Horse Racing","PageTitle":"Filtered applied. EventID: 122024517","TimeStamp":"10\/07\/22 18:27:49"},"Event":{"@attributes":{"Name":"Race 7 Donald","ID":"122024517","OffTime":"11\/07\/22 06:30:00","EventComment":"","Going":"Firm","RaceType":"Flat","RaceDistance":"1350m","PlaceCount":"3","PlaceOdds":"1\/5","PGID":"122024517"},"Market":[{"@attributes":{"Name":"Top Fluc","ID":"20103","FID":"122024517"},"Participant":[{"@attributes":{"Name":"Eitilt","Odds":"SP","OddsDecimal":"SP","OddsAmerican":"SP","RaceOffOdds":"","SaddleCloth":"1","ID":"1266311981","LastUpdated":"08\/07\/22 02:37:27","AVG":"1D95552ABABB845BAE60C1AE3CB6D1A2CC981413"}},{"@attributes":{"Name":"Nightstick","Odds":"NR","OddsDecimal":"NR","OddsAmerican":"NR","RaceOffOdds":"","SaddleCloth":"2","ID":"1266312036","LastUpdated":"09\/07\/22 23:02:49","AVG":"7D317FD9236E3C6D2C072080E2CFDBE2571E307C"}},{"@attributes":{"Name":"Sizzling Sonata","Odds":"SP","OddsDecimal":"SP","OddsAmerican":"SP","RaceOffOdds":"","SaddleCloth":"3","ID":"1266312053","LastUpdated":"08\/07\/22 02:37:29","AVG":"C4C688169DA4635960D04DDAB52E6408E9BB0C82"}},{"@attributes":{"Name":"Almighty Will","Odds":"SP","OddsDecimal":"SP","OddsAmerican":"SP","RaceOffOdds":"","SaddleCloth":"4","ID":"1266312070","LastUpdated":"08\/07\/22 02:37:30","AVG":"FE09F8A344DCFCC9BDDB7D1084BB19C0451A1CA7"}},{"@attributes":{"Name":"Rock Wave","Odds":"SP","OddsDecimal":"SP","OddsAmerican":"SP","RaceOffOdds":"","SaddleCloth":"5","ID":"1266312091","LastUpdated":"08\/07\/22 02:37:30","AVG":"371FBF4680BBE2C390A2D416AED0B5BF65678D6C"}},{"@attributes":{"Name":"Fast Melody","Odds":"SP","OddsDecimal":"SP","OddsAmerican":"SP","RaceOffOdds":"","SaddleCloth":"6","ID":"1266312116","LastUpdated":"08\/07\/22 02:37:31","AVG":"E0D91C744D322768B6B3707E5F0E474ABA10FD51"}},{"@attributes":{"Name":"Ulanni","Odds":"SP","OddsDecimal":"SP","OddsAmerican":"SP","RaceOffOdds":"","SaddleCloth":"7","ID":"1266312185","LastUpdated":"08\/07\/22 02:37:31","AVG":"ADF09FA9E14F318B15D53E6452116779DA4BE27B"}},{"@attributes":{"Name":"Make Mine Hennessy","Odds":"NR","OddsDecimal":"NR","OddsAmerican":"NR","RaceOffOdds":"","SaddleCloth":"8","ID":"1266312267","LastUpdated":"10\/07\/22 00:27:52","AVG":"40125C166CD36BDEE8872D6EA99D994BF73A53C4"}},{"@attributes":{"Name":"My Divas","Odds":"SP","OddsDecimal":"SP","OddsAmerican":"SP","RaceOffOdds":"","SaddleCloth":"9","ID":"1266312336","LastUpdated":"08\/07\/22 02:37:32","AVG":"7210A88D4DE289DF05BFEABBD742AFDA76785235"}},{"@attributes":{"Name":"Rojean","Odds":"SP","OddsDecimal":"SP","OddsAmerican":"SP","RaceOffOdds":"","SaddleCloth":"10","ID":"1266312401","LastUpdated":"08\/07\/22 02:37:33","AVG":"F1ED43BBDDCAFB02303AA44DB345509BEBDF5778"}},{"@attributes":{"Name":"Annie's Comet","Odds":"SP","OddsDecimal":"SP","OddsAmerican":"SP","RaceOffOdds":"","SaddleCloth":"11","ID":"1266312459","LastUpdated":"08\/07\/22 02:37:33","AVG":"F0AE7DB9AD60FE235314CA3A83326F52AC248958"}},{"@attributes":{"Name":"Romanesco Fresco","Odds":"SP","OddsDecimal":"SP","OddsAmerican":"SP","RaceOffOdds":"","SaddleCloth":"12","ID":"1266312534","LastUpdated":"08\/07\/22 02:37:34","AVG":"94A8053ED67AEC0468E4E3482DD2B735EF40B947"}},{"@attributes":{"Name":"Last Hope","Odds":"SP","OddsDecimal":"SP","OddsAmerican":"SP","RaceOffOdds":"","SaddleCloth":"13","ID":"1266312587","LastUpdated":"08\/07\/22 02:37:34","AVG":"033059A6AF8F8614DDB6B75FAE3EF95D72A87639"}},{"@attributes":{"Name":"Fontaine Del Rosso","Odds":"SP","OddsDecimal":"SP","OddsAmerican":"SP","RaceOffOdds":"","SaddleCloth":"14","ID":"1266312663","LastUpdated":"08\/07\/22 02:37:35","AVG":"63F619BB5B2AA65619C7F9DDF5BB1E328D385696"}},{"@attributes":{"Name":"Bonjour","Odds":"SP","OddsDecimal":"SP","OddsAmerican":"SP","RaceOffOdds":"","SaddleCloth":"15","ID":"1266312744","LastUpdated":"08\/07\/22 02:37:35","AVG":"31D6B86BCD9BE653D1173408D252D17664775875"}},{"@attributes":{"Name":"Helene's Era","Odds":"NR","OddsDecimal":"NR","OddsAmerican":"NR","RaceOffOdds":"","SaddleCloth":"16","ID":"1266312815","LastUpdated":"10\/07\/22 00:27:53","AVG":"FAA93844869B84F2EE96FA3F8CDC7B37800E1511"}},{"@attributes":{"Name":"Opicina","Odds":"SP","OddsDecimal":"SP","OddsAmerican":"SP","RaceOffOdds":"","SaddleCloth":"17","ID":"1266312914","LastUpdated":"08\/07\/22 02:37:36","AVG":"6F7BDB1B686565F6C948642D12DF7FA22FA3890C"}},{"@attributes":{"Name":"Franquin","Odds":"SP","OddsDecimal":"SP","OddsAmerican":"SP","RaceOffOdds":"","SaddleCloth":"18","ID":"1266312994","LastUpdated":"08\/07\/22 02:37:36","AVG":"C17C7516997A03B6D5C0CC38D1AA0BE591804AEA"}}]},{"@attributes":{"Name":"Fixed Win","ID":"20203","FID":"122024517"},"Participant":[{"@attributes":{"Name":"Eitilt","Odds":"14\/1","OddsDecimal":"15.00","OddsAmerican":"1400","RaceOffOdds":"","SaddleCloth":"1","ID":"1266311944","LastUpdated":"10\/07\/22 13:28:29","AVG":"29A1C76C4FBC6FB76F25521AFE8A99763BD1B6DB"}},{"@attributes":{"Name":"Nightstick","Odds":"NR","OddsDecimal":"NR","OddsAmerican":"NR","RaceOffOdds":"","SaddleCloth":"2","ID":"1266312032","LastUpdated":"09\/07\/22 23:02:49","AVG":"B800922E80BC6CD699B764E9453DCC94827A643F"}},{"@attributes":{"Name":"Sizzling Sonata","Odds":"13\/10","OddsDecimal":"2.30","OddsAmerican":"130","RaceOffOdds":"","SaddleCloth":"3","ID":"1266312049","LastUpdated":"10\/07\/22 13:28:29","AVG":"B0497D40BE7200F295D2A7675A7668722C8FCBAD"}},{"@attributes":{"Name":"Almighty Will","Odds":"12\/1","OddsDecimal":"13.00","OddsAmerican":"1200","RaceOffOdds":"","SaddleCloth":"4","ID":"1266312066","LastUpdated":"10\/07\/22 17:00:20","AVG":"D8A025FF8EF35D35ED60B9701F7061AB77A65373"}},{"@attributes":{"Name":"Rock Wave","Odds":"15\/1","OddsDecimal":"16.00","OddsAmerican":"1500","RaceOffOdds":"","SaddleCloth":"5","ID":"1266312087","LastUpdated":"10\/07\/22 13:28:29","AVG":"43F251A25D9FC162C8B8EF1872A391DB1CFC541C"}},{"@attributes":{"Name":"Fast Melody","Odds":"11\/2","OddsDecimal":"6.50","OddsAmerican":"550","RaceOffOdds":"","SaddleCloth":"6","ID":"1266312107","LastUpdated":"10\/07\/22 17:02:52","AVG":"78FC6BE495D05F8D7490AE70CF6A5649F2B429E1"}},{"@attributes":{"Name":"Ulanni","Odds":"16\/1","OddsDecimal":"17.00","OddsAmerican":"1600","RaceOffOdds":"","SaddleCloth":"7","ID":"1266312163","LastUpdated":"10\/07\/22 13:19:58","AVG":"677C9F71269F05280AF34067442B22E2F28D9684"}},{"@attributes":{"Name":"Make Mine Hennessy","Odds":"NR","OddsDecimal":"NR","OddsAmerican":"NR","RaceOffOdds":"","SaddleCloth":"8","ID":"1266312246","LastUpdated":"10\/07\/22 00:27:52","AVG":"A52E3CFC76C0EB37C018004BAFA91D2B04E948D2"}},{"@attributes":{"Name":"My Divas","Odds":"18\/1","OddsDecimal":"19.00","OddsAmerican":"1800","RaceOffOdds":"","SaddleCloth":"9","ID":"1266312317","LastUpdated":"10\/07\/22 17:00:20","AVG":"2E1106164E620CDBD07196EB8F9689BFA2CC0E94"}},{"@attributes":{"Name":"Rojean","Odds":"3\/1","OddsDecimal":"4.00","OddsAmerican":"300","RaceOffOdds":"","SaddleCloth":"10","ID":"1266312385","LastUpdated":"10\/07\/22 13:28:29","AVG":"14FDF6CA6483F0EEC016AE9129624DC31333244A"}},{"@attributes":{"Name":"Annie's Comet","Odds":"18\/1","OddsDecimal":"19.00","OddsAmerican":"1800","RaceOffOdds":"","SaddleCloth":"11","ID":"1266312440","LastUpdated":"10\/07\/22 17:00:20","AVG":"F020AAFF37887B22D35C197BBC734CFB2DEC7E60"}},{"@attributes":{"Name":"Romanesco Fresco","Odds":"25\/1","OddsDecimal":"26.00","OddsAmerican":"2500","RaceOffOdds":"","SaddleCloth":"12","ID":"1266312512","LastUpdated":"10\/07\/22 13:21:12","AVG":"0BAE61AD20CED0F4BA95E2336A5C06F25639BB87"}},{"@attributes":{"Name":"Last Hope","Odds":"20\/1","OddsDecimal":"21.00","OddsAmerican":"2000","RaceOffOdds":"","SaddleCloth":"13","ID":"1266312574","LastUpdated":"10\/07\/22 09:47:16","AVG":"EBDD81911A3CF8EDA377039F5E62A7F7B60286F9"}},{"@attributes":{"Name":"Fontaine Del Rosso","Odds":"100\/1","OddsDecimal":"101.00","OddsAmerican":"10000","RaceOffOdds":"","SaddleCloth":"14","ID":"1266312641","LastUpdated":"10\/07\/22 13:08:10","AVG":"7C40D9C75C7B1CC17EA8F48980B73117CAB15D02"}},{"@attributes":{"Name":"Bonjour","Odds":"8\/1","OddsDecimal":"9.00","OddsAmerican":"800","RaceOffOdds":"","SaddleCloth":"15","ID":"1266312722","LastUpdated":"10\/07\/22 15:00:19","AVG":"18E7B975921C77FA8BA7EA929DC2319F4506797E"}},{"@attributes":{"Name":"Helene's Era","Odds":"NR","OddsDecimal":"NR","OddsAmerican":"NR","RaceOffOdds":"","SaddleCloth":"16","ID":"1266312797","LastUpdated":"10\/07\/22 00:27:53","AVG":"3ADCF74CB4614B8B27D555BFB335FAFB83EBB852"}},{"@attributes":{"Name":"Opicina","Odds":"80\/1","OddsDecimal":"81.00","OddsAmerican":"8000","RaceOffOdds":"","SaddleCloth":"17","ID":"1266312885","LastUpdated":"10\/07\/22 17:00:20","AVG":"04413BB54D549592BBDEEE37C5E3E1C5DFE5DE00"}},{"@attributes":{"Name":"Franquin","Odds":"70\/1","OddsDecimal":"71.00","OddsAmerican":"7000","RaceOffOdds":"","SaddleCloth":"18","ID":"1266312974","LastUpdated":"10\/07\/22 17:02:52","AVG":"255B1EBFD6E53DD3A00C550473DE80DEF8AE2E66"}}]},{"@attributes":{"Name":"Fixed Place","ID":"20204","FID":"122024517"},"Participant":[{"@attributes":{"Name":"Eitilt","Odds":"29\/10","OddsDecimal":"3.90","OddsAmerican":"290","RaceOffOdds":"","SaddleCloth":"1","ID":"1266311958","LastUpdated":"10\/07\/22 17:02:52","AVG":"0256017E715E1659FA55CE40DDECBB78E4DA9748"}},{"@attributes":{"Name":"Sizzling Sonata","Odds":"2\/5","OddsDecimal":"1.40","OddsAmerican":"-250","RaceOffOdds":"","SaddleCloth":"3","ID":"1266312050","LastUpdated":"10\/07\/22 13:28:29","AVG":"BC65A8C7E8C93AC4BA7C5BDE1EF984A64F577F04"}},{"@attributes":{"Name":"Almighty Will","Odds":"5\/2","OddsDecimal":"3.50","OddsAmerican":"250","RaceOffOdds":"","SaddleCloth":"4","ID":"1266312067","LastUpdated":"10\/07\/22 17:00:20","AVG":"7E82734533B9F0C21B21E46DAA3FFD7859D8EC0A"}},{"@attributes":{"Name":"Rock Wave","Odds":"3\/1","OddsDecimal":"4.00","OddsAmerican":"300","RaceOffOdds":"","SaddleCloth":"5","ID":"1266312088","LastUpdated":"10\/07\/22 13:28:29","AVG":"0B43BD1771BD279079B2FC2A978F7DA12DB39B9F"}},{"@attributes":{"Name":"Fast Melody","Odds":"5\/4","OddsDecimal":"2.25","OddsAmerican":"125","RaceOffOdds":"","SaddleCloth":"6","ID":"1266312112","LastUpdated":"10\/07\/22 17:02:52","AVG":"7EEA6585ED8A33D25514BBE6326F1650A4E51063"}},{"@attributes":{"Name":"Ulanni","Odds":"16\/5","OddsDecimal":"4.20","OddsAmerican":"320","RaceOffOdds":"","SaddleCloth":"7","ID":"1266312168","LastUpdated":"10\/07\/22 13:19:58","AVG":"9B7E006B03290BDBA973F576EF7002CBE3C558E6"}},{"@attributes":{"Name":"My Divas","Odds":"17\/5","OddsDecimal":"4.40","OddsAmerican":"340","RaceOffOdds":"","SaddleCloth":"9","ID":"1266312321","LastUpdated":"10\/07\/22 17:00:20","AVG":"D60846E67B0F7F600A3D5DBFCB21172E0E6E1D45"}},{"@attributes":{"Name":"Rojean","Odds":"4\/5","OddsDecimal":"1.80","OddsAmerican":"-125","RaceOffOdds":"","SaddleCloth":"10","ID":"1266312389","LastUpdated":"10\/07\/22 13:28:29","AVG":"CAAD13A7DB1B32BE5B46B59BECCCF2026781CE01"}},{"@attributes":{"Name":"Annie's Comet","Odds":"17\/5","OddsDecimal":"4.40","OddsAmerican":"340","RaceOffOdds":"","SaddleCloth":"11","ID":"1266312445","LastUpdated":"10\/07\/22 17:00:20","AVG":"88599B9B5C405AB4489D1087773291B7C5D92CC7"}},{"@attributes":{"Name":"Romanesco Fresco","Odds":"5\/1","OddsDecimal":"6.00","OddsAmerican":"500","RaceOffOdds":"","SaddleCloth":"12","ID":"1266312518","LastUpdated":"10\/07\/22 13:21:12","AVG":"EEA4AC8264BD8867EFCE71B1B870D06E8B8F7A18"}},{"@attributes":{"Name":"Last Hope","Odds":"19\/5","OddsDecimal":"4.80","OddsAmerican":"380","RaceOffOdds":"","SaddleCloth":"13","ID":"1266312575","LastUpdated":"10\/07\/22 17:02:52","AVG":"6C06119D6DD5DF03B87DA45BBFFFD894D9162DD2"}},{"@attributes":{"Name":"Fontaine Del Rosso","Odds":"22\/1","OddsDecimal":"23.00","OddsAmerican":"2200","RaceOffOdds":"","SaddleCloth":"14","ID":"1266312646","LastUpdated":"10\/07\/22 13:08:10","AVG":"FE94FCF13975989BDB15E4DA190B2DF4366A9F2D"}},{"@attributes":{"Name":"Bonjour","Odds":"7\/4","OddsDecimal":"2.75","OddsAmerican":"175","RaceOffOdds":"","SaddleCloth":"15","ID":"1266312728","LastUpdated":"10\/07\/22 17:00:20","AVG":"8A7E1652A5ED98EC1F825F909E29FD1CE4F6A4B3"}},{"@attributes":{"Name":"Opicina","Odds":"18\/1","OddsDecimal":"19.00","OddsAmerican":"1800","RaceOffOdds":"","SaddleCloth":"17","ID":"1266312897","LastUpdated":"10\/07\/22 17:00:20","AVG":"9126E3D808CA7DAF5B4EAAFBCDE0DB8A05683C91"}},{"@attributes":{"Name":"Franquin","Odds":"15\/1","OddsDecimal":"16.00","OddsAmerican":"1500","RaceOffOdds":"","SaddleCloth":"18","ID":"1266312979","LastUpdated":"10\/07\/22 17:02:52","AVG":"B55D907102230814819431ED078E53FA318FC028"}}]},{"@attributes":{"Name":"Tote Win","ID":"20205","FID":"122024517"},"Participant":[{"@attributes":{"Name":"Eitilt","Odds":"SP","OddsDecimal":"SP","OddsAmerican":"SP","RaceOffOdds":"","SaddleCloth":"1","ID":"1266311965","LastUpdated":"08\/07\/22 02:37:27","AVG":"A39BF8ECC0DACAA7F882A80BB939156C452787B8"}},{"@attributes":{"Name":"Nightstick","Odds":"NR","OddsDecimal":"NR","OddsAmerican":"NR","RaceOffOdds":"","SaddleCloth":"2","ID":"1266312034","LastUpdated":"09\/07\/22 23:02:49","AVG":"E87308B3781BFA7513A2BE2C4C7752045C2E2CDC"}},{"@attributes":{"Name":"Sizzling Sonata","Odds":"SP","OddsDecimal":"SP","OddsAmerican":"SP","RaceOffOdds":"","SaddleCloth":"3","ID":"1266312051","LastUpdated":"08\/07\/22 02:37:29","AVG":"253F5CE4A60E1D6D762B4F3E1CF9AE583DE359F7"}},{"@attributes":{"Name":"Almighty Will","Odds":"SP","OddsDecimal":"SP","OddsAmerican":"SP","RaceOffOdds":"","SaddleCloth":"4","ID":"1266312068","LastUpdated":"08\/07\/22 02:37:30","AVG":"6A78EF887ACBA030D6D8C4C8B595F17F37716798"}},{"@attributes":{"Name":"Rock Wave","Odds":"SP","OddsDecimal":"SP","OddsAmerican":"SP","RaceOffOdds":"","SaddleCloth":"5","ID":"1266312089","LastUpdated":"08\/07\/22 02:37:30","AVG":"588CD9C492602E73A2806812F4BBDC43EAC75573"}},{"@attributes":{"Name":"Fast Melody","Odds":"SP","OddsDecimal":"SP","OddsAmerican":"SP","RaceOffOdds":"","SaddleCloth":"6","ID":"1266312114","LastUpdated":"08\/07\/22 02:37:31","AVG":"B8085DF91EE9D28C4C14F132BDA8618C277A0638"}},{"@attributes":{"Name":"Ulanni","Odds":"SP","OddsDecimal":"SP","OddsAmerican":"SP","RaceOffOdds":"","SaddleCloth":"7","ID":"1266312174","LastUpdated":"08\/07\/22 02:37:31","AVG":"A918E150AAF70605CC1E4E672B367B8B8250ECF1"}},{"@attributes":{"Name":"Make Mine Hennessy","Odds":"NR","OddsDecimal":"NR","OddsAmerican":"NR","RaceOffOdds":"","SaddleCloth":"8","ID":"1266312257","LastUpdated":"10\/07\/22 00:27:52","AVG":"30D79C66691BD655F3054B2A9758C3737D7FDD51"}},{"@attributes":{"Name":"My Divas","Odds":"SP","OddsDecimal":"SP","OddsAmerican":"SP","RaceOffOdds":"","SaddleCloth":"9","ID":"1266312326","LastUpdated":"08\/07\/22 02:37:32","AVG":"DC7F7102B462732B36AB9D9C2530EC02474A7011"}},{"@attributes":{"Name":"Rojean","Odds":"SP","OddsDecimal":"SP","OddsAmerican":"SP","RaceOffOdds":"","SaddleCloth":"10","ID":"1266312394","LastUpdated":"08\/07\/22 02:37:33","AVG":"1A375EEDC16A543537D28B4281C2DB117D3D6A7F"}},{"@attributes":{"Name":"Annie's Comet","Odds":"SP","OddsDecimal":"SP","OddsAmerican":"SP","RaceOffOdds":"","SaddleCloth":"11","ID":"1266312451","LastUpdated":"08\/07\/22 02:37:33","AVG":"DCB0CD58343B0D6838D430EEA9434CD5F5E071E0"}},{"@attributes":{"Name":"Romanesco Fresco","Odds":"SP","OddsDecimal":"SP","OddsAmerican":"SP","RaceOffOdds":"","SaddleCloth":"12","ID":"1266312523","LastUpdated":"08\/07\/22 02:37:34","AVG":"F52551587726AE7BB04F59EBA6DA32AD52EB1963"}},{"@attributes":{"Name":"Last Hope","Odds":"SP","OddsDecimal":"SP","OddsAmerican":"SP","RaceOffOdds":"","SaddleCloth":"13","ID":"1266312576","LastUpdated":"08\/07\/22 02:37:34","AVG":"218EE8FF9015C5E5A6D91C2C6E16FDFA5C1FA1C8"}},{"@attributes":{"Name":"Fontaine Del Rosso","Odds":"SP","OddsDecimal":"SP","OddsAmerican":"SP","RaceOffOdds":"","SaddleCloth":"14","ID":"1266312651","LastUpdated":"08\/07\/22 02:37:34","AVG":"4FD59DDA3825C25AAF03F099770D295EBD851188"}},{"@attributes":{"Name":"Bonjour","Odds":"SP","OddsDecimal":"SP","OddsAmerican":"SP","RaceOffOdds":"","SaddleCloth":"15","ID":"1266312733","LastUpdated":"08\/07\/22 02:37:35","AVG":"4476EFA3ED1B372DA67DB7FFBA98449ADD2F8BCA"}},{"@attributes":{"Name":"Helene's Era","Odds":"NR","OddsDecimal":"NR","OddsAmerican":"NR","RaceOffOdds":"","SaddleCloth":"16","ID":"1266312805","LastUpdated":"10\/07\/22 00:27:53","AVG":"41A10D0A240714E4545B453543581A5B0B722A38"}},{"@attributes":{"Name":"Opicina","Odds":"SP","OddsDecimal":"SP","OddsAmerican":"SP","RaceOffOdds":"","SaddleCloth":"17","ID":"1266312904","LastUpdated":"08\/07\/22 02:37:36","AVG":"CAB580B1052BC0F7F4DFA8898CDB57AD973CB000"}},{"@attributes":{"Name":"Franquin","Odds":"SP","OddsDecimal":"SP","OddsAmerican":"SP","RaceOffOdds":"","SaddleCloth":"18","ID":"1266312984","LastUpdated":"08\/07\/22 02:37:36","AVG":"EFBDE0114449968E6D0CB82C9CDC759F4B1EB9C1"}}]},{"@attributes":{"Name":"Tote Place","ID":"20206","FID":"122024517"},"Participant":[{"@attributes":{"Name":"Eitilt","Odds":"SP","OddsDecimal":"SP","OddsAmerican":"SP","RaceOffOdds":"","SaddleCloth":"1","ID":"1266311974","LastUpdated":"08\/07\/22 02:37:27","AVG":"4DF731429C9DC6DC7013273CF88FDB1B6EA96953"}},{"@attributes":{"Name":"Nightstick","Odds":"NR","OddsDecimal":"NR","OddsAmerican":"NR","RaceOffOdds":"","SaddleCloth":"2","ID":"1266312035","LastUpdated":"09\/07\/22 23:02:49","AVG":"61198B31C6C6ACAC3FC38B59C1C6B1E7BB02CE48"}},{"@attributes":{"Name":"Sizzling Sonata","Odds":"SP","OddsDecimal":"SP","OddsAmerican":"SP","RaceOffOdds":"","SaddleCloth":"3","ID":"1266312052","LastUpdated":"08\/07\/22 02:37:29","AVG":"1645E20DC7823997EE9E7A319F47887EADE99E6B"}},{"@attributes":{"Name":"Almighty Will","Odds":"SP","OddsDecimal":"SP","OddsAmerican":"SP","RaceOffOdds":"","SaddleCloth":"4","ID":"1266312069","LastUpdated":"08\/07\/22 02:37:30","AVG":"7EEDA566A6901B6D7B2C730E5FB1E4A5FD30A40D"}},{"@attributes":{"Name":"Rock Wave","Odds":"SP","OddsDecimal":"SP","OddsAmerican":"SP","RaceOffOdds":"","SaddleCloth":"5","ID":"1266312090","LastUpdated":"08\/07\/22 02:37:30","AVG":"EE5A087FE70CF0022F0CF696FBE4F791D26E409D"}},{"@attributes":{"Name":"Fast Melody","Odds":"SP","OddsDecimal":"SP","OddsAmerican":"SP","RaceOffOdds":"","SaddleCloth":"6","ID":"1266312115","LastUpdated":"08\/07\/22 02:37:31","AVG":"C11EA12C81F239697431DD9EF772A4E372E133CA"}},{"@attributes":{"Name":"Ulanni","Odds":"SP","OddsDecimal":"SP","OddsAmerican":"SP","RaceOffOdds":"","SaddleCloth":"7","ID":"1266312180","LastUpdated":"08\/07\/22 02:37:31","AVG":"E18714884F3FD428DD4970FD494B6F9F75E697F1"}},{"@attributes":{"Name":"Make Mine Hennessy","Odds":"NR","OddsDecimal":"NR","OddsAmerican":"NR","RaceOffOdds":"","SaddleCloth":"8","ID":"1266312262","LastUpdated":"10\/07\/22 00:27:52","AVG":"1FB6CF98C376141298F84473F6DEB0C33BBBE886"}},{"@attributes":{"Name":"My Divas","Odds":"SP","OddsDecimal":"SP","OddsAmerican":"SP","RaceOffOdds":"","SaddleCloth":"9","ID":"1266312332","LastUpdated":"08\/07\/22 02:37:32","AVG":"02A22E5820C248BE7DE0018AE874FD7D6E3A6A5F"}},{"@attributes":{"Name":"Rojean","Odds":"SP","OddsDecimal":"SP","OddsAmerican":"SP","RaceOffOdds":"","SaddleCloth":"10","ID":"1266312399","LastUpdated":"08\/07\/22 02:37:33","AVG":"83CAF78D5608AAF3087D9A3992560592A20E7E9B"}},{"@attributes":{"Name":"Annie's Comet","Odds":"SP","OddsDecimal":"SP","OddsAmerican":"SP","RaceOffOdds":"","SaddleCloth":"11","ID":"1266312455","LastUpdated":"08\/07\/22 02:37:33","AVG":"8F4B12F30B78569322AB3943AED1F22F65C6675F"}},{"@attributes":{"Name":"Romanesco Fresco","Odds":"SP","OddsDecimal":"SP","OddsAmerican":"SP","RaceOffOdds":"","SaddleCloth":"12","ID":"1266312528","LastUpdated":"08\/07\/22 02:37:34","AVG":"4DF0FF45B18D2428A240050322DBBDC5ED4391E0"}},{"@attributes":{"Name":"Last Hope","Odds":"SP","OddsDecimal":"SP","OddsAmerican":"SP","RaceOffOdds":"","SaddleCloth":"13","ID":"1266312582","LastUpdated":"08\/07\/22 02:37:34","AVG":"570B52E01FBB50B7A3A6389DCAAEB42D9447793A"}},{"@attributes":{"Name":"Fontaine Del Rosso","Odds":"SP","OddsDecimal":"SP","OddsAmerican":"SP","RaceOffOdds":"","SaddleCloth":"14","ID":"1266312657","LastUpdated":"08\/07\/22 02:37:34","AVG":"F283ACF1BF1BD3700FD2300363CDFAC9F9519970"}},{"@attributes":{"Name":"Bonjour","Odds":"SP","OddsDecimal":"SP","OddsAmerican":"SP","RaceOffOdds":"","SaddleCloth":"15","ID":"1266312738","LastUpdated":"08\/07\/22 02:37:35","AVG":"6DA5523DA5730E38B77ACBC83D72AB7D2B33860C"}},{"@attributes":{"Name":"Helene's Era","Odds":"NR","OddsDecimal":"NR","OddsAmerican":"NR","RaceOffOdds":"","SaddleCloth":"16","ID":"1266312811","LastUpdated":"10\/07\/22 00:27:53","AVG":"61397C166693EADA263AE1227FB4A3C69B85FA5B"}},{"@attributes":{"Name":"Opicina","Odds":"SP","OddsDecimal":"SP","OddsAmerican":"SP","RaceOffOdds":"","SaddleCloth":"17","ID":"1266312908","LastUpdated":"08\/07\/22 02:37:36","AVG":"924BF6C69929F1B5889B9F5954AA66B02908F039"}},{"@attributes":{"Name":"Franquin","Odds":"SP","OddsDecimal":"SP","OddsAmerican":"SP","RaceOffOdds":"","SaddleCloth":"18","ID":"1266312989","LastUpdated":"08\/07\/22 02:37:36","AVG":"0DCD9BBFFB6B23E650CBE0B8AE84DBA1EC0F60A4"}}]},{"@attributes":{"Name":"Cover Bet 2 places","ID":"20207","FID":"122024517"},"Participant":[{"@attributes":{"Name":"Eitilt","Odds":"12\/1","OddsDecimal":"13.00","OddsAmerican":"1200","RaceOffOdds":"","SaddleCloth":"1","ID":"1266311989","LastUpdated":"10\/07\/22 13:28:29","AVG":"D3661BEE2E3A83EBAB5154D078C024258318FD3A"}},{"@attributes":{"Name":"Sizzling Sonata","Odds":"9\/10","OddsDecimal":"1.90","OddsAmerican":"-111","RaceOffOdds":"","SaddleCloth":"3","ID":"1266312054","LastUpdated":"10\/07\/22 13:28:29","AVG":"150ED5FE2B9C96DEEA0B17C2B59FA563AF9FEE95"}},{"@attributes":{"Name":"Almighty Will","Odds":"10\/1","OddsDecimal":"11.00","OddsAmerican":"1000","RaceOffOdds":"","SaddleCloth":"4","ID":"1266312071","LastUpdated":"10\/07\/22 17:00:20","AVG":"23B0AABEA977CA07B23E441F501213A18F742315"}},{"@attributes":{"Name":"Rock Wave","Odds":"13\/1","OddsDecimal":"14.00","OddsAmerican":"1300","RaceOffOdds":"","SaddleCloth":"5","ID":"1266312092","LastUpdated":"10\/07\/22 13:28:29","AVG":"1C3AD9166D164284192090E4C98EF2A543B7D585"}},{"@attributes":{"Name":"Fast Melody","Odds":"9\/2","OddsDecimal":"5.50","OddsAmerican":"450","RaceOffOdds":"","SaddleCloth":"6","ID":"1266312121","LastUpdated":"10\/07\/22 17:02:52","AVG":"0E89B3CC005CEB04346DFF728EC25B5890F70F0E"}},{"@attributes":{"Name":"Ulanni","Odds":"14\/1","OddsDecimal":"15.00","OddsAmerican":"1400","RaceOffOdds":"","SaddleCloth":"7","ID":"1266312190","LastUpdated":"10\/07\/22 13:19:58","AVG":"BBE79F74537C2B7E9ACE3EA05C4E6631E6F72E74"}},{"@attributes":{"Name":"My Divas","Odds":"16\/1","OddsDecimal":"17.00","OddsAmerican":"1600","RaceOffOdds":"","SaddleCloth":"9","ID":"1266312340","LastUpdated":"10\/07\/22 17:00:20","AVG":"512BBA39AADC48958D0F445130DF928016497428"}},{"@attributes":{"Name":"Rojean","Odds":"23\/10","OddsDecimal":"3.30","OddsAmerican":"230","RaceOffOdds":"","SaddleCloth":"10","ID":"1266312403","LastUpdated":"10\/07\/22 13:28:29","AVG":"710A91BAE43011971B4D7E97B6D2B81A80228B6E"}},{"@attributes":{"Name":"Annie's Comet","Odds":"16\/1","OddsDecimal":"17.00","OddsAmerican":"1600","RaceOffOdds":"","SaddleCloth":"11","ID":"1266312461","LastUpdated":"10\/07\/22 17:00:20","AVG":"A3AD15E33FDBDC9D51665AC41AA882E2A40FE10F"}},{"@attributes":{"Name":"Romanesco Fresco","Odds":"22\/1","OddsDecimal":"23.00","OddsAmerican":"2200","RaceOffOdds":"","SaddleCloth":"12","ID":"1266312538","LastUpdated":"10\/07\/22 13:21:13","AVG":"F873BADBB44B20CF05F15DCDF9C676E658459CC7"}},{"@attributes":{"Name":"Last Hope","Odds":"18\/1","OddsDecimal":"19.00","OddsAmerican":"1800","RaceOffOdds":"","SaddleCloth":"13","ID":"1266312593","LastUpdated":"10\/07\/22 08:30:07","AVG":"F92881C41734D4A7FF6463C70A220CAA1F04294F"}},{"@attributes":{"Name":"Fontaine Del Rosso","Odds":"90\/1","OddsDecimal":"91.00","OddsAmerican":"9000","RaceOffOdds":"","SaddleCloth":"14","ID":"1266312670","LastUpdated":"10\/07\/22 13:08:10","AVG":"76FA053F58790939501EC0502F89F3F5ECE4999F"}},{"@attributes":{"Name":"Bonjour","Odds":"13\/2","OddsDecimal":"7.50","OddsAmerican":"650","RaceOffOdds":"","SaddleCloth":"15","ID":"1266312749","LastUpdated":"10\/07\/22 16:49:47","AVG":"1213BF40529FDB0C14088AC0F10E1E462D6681B2"}},{"@attributes":{"Name":"Opicina","Odds":"70\/1","OddsDecimal":"71.00","OddsAmerican":"7000","RaceOffOdds":"","SaddleCloth":"17","ID":"1266312920","LastUpdated":"10\/07\/22 17:00:20","AVG":"7A93D6425E9D63A73287F6A24EAD798868068A84"}},{"@attributes":{"Name":"Franquin","Odds":"60\/1","OddsDecimal":"61.00","OddsAmerican":"6000","RaceOffOdds":"","SaddleCloth":"18","ID":"1266312999","LastUpdated":"10\/07\/22 17:02:52","AVG":"1D658185E15EB0E34B074C32B90229DF07FAA610"}}]},{"@attributes":{"Name":"Cover Bet 3 places","ID":"20208","FID":"122024517"},"Participant":[{"@attributes":{"Name":"Eitilt","Odds":"11\/1","OddsDecimal":"12.00","OddsAmerican":"1100","RaceOffOdds":"","SaddleCloth":"1","ID":"1266311997","LastUpdated":"10\/07\/22 13:28:29","AVG":"E1079E3ACC17CBF34E0C17681E0F7470008ED6E7"}},{"@attributes":{"Name":"Sizzling Sonata","Odds":"13\/20","OddsDecimal":"1.65","OddsAmerican":"-154","RaceOffOdds":"","SaddleCloth":"3","ID":"1266312055","LastUpdated":"10\/07\/22 13:28:29","AVG":"AA5C94AE91E9785A19982BA87ED4743F2B539CE9"}},{"@attributes":{"Name":"Almighty Will","Odds":"9\/1","OddsDecimal":"10.00","OddsAmerican":"900","RaceOffOdds":"","SaddleCloth":"4","ID":"1266312072","LastUpdated":"10\/07\/22 17:00:20","AVG":"9B2F6D57B759B3F32798EA13A6AB5E600C5A941A"}},{"@attributes":{"Name":"Rock Wave","Odds":"12\/1","OddsDecimal":"13.00","OddsAmerican":"1200","RaceOffOdds":"","SaddleCloth":"5","ID":"1266312093","LastUpdated":"10\/07\/22 13:28:29","AVG":"D39E3D8F358A701C7FB2992D4F3FC78F94628CC0"}},{"@attributes":{"Name":"Fast Melody","Odds":"18\/5","OddsDecimal":"4.60","OddsAmerican":"360","RaceOffOdds":"","SaddleCloth":"6","ID":"1266312122","LastUpdated":"10\/07\/22 17:02:52","AVG":"AC9B4D223E8F42C46DC9523EA45F896356DBE7AC"}},{"@attributes":{"Name":"Ulanni","Odds":"12\/1","OddsDecimal":"13.00","OddsAmerican":"1200","RaceOffOdds":"","SaddleCloth":"7","ID":"1266312195","LastUpdated":"10\/07\/22 13:08:10","AVG":"7E34FF2230A2DFBF2373F604A5A24EFCD4D5D5EC"}},{"@attributes":{"Name":"My Divas","Odds":"14\/1","OddsDecimal":"15.00","OddsAmerican":"1400","RaceOffOdds":"","SaddleCloth":"9","ID":"1266312346","LastUpdated":"10\/07\/22 17:00:20","AVG":"670DB9193A23C48E5CBF0781876FF1DEFA0D7C9B"}},{"@attributes":{"Name":"Rojean","Odds":"7\/4","OddsDecimal":"2.75","OddsAmerican":"175","RaceOffOdds":"","SaddleCloth":"10","ID":"1266312405","LastUpdated":"10\/07\/22 13:28:29","AVG":"B8E8DDC026D99F48C2FB96A76A6179E1EB6A2048"}},{"@attributes":{"Name":"Annie's Comet","Odds":"14\/1","OddsDecimal":"15.00","OddsAmerican":"1400","RaceOffOdds":"","SaddleCloth":"11","ID":"1266312466","LastUpdated":"10\/07\/22 17:00:20","AVG":"7AD81770DE56F78AFA655C4C746AD3DEA66163FF"}},{"@attributes":{"Name":"Romanesco Fresco","Odds":"20\/1","OddsDecimal":"21.00","OddsAmerican":"2000","RaceOffOdds":"","SaddleCloth":"12","ID":"1266312544","LastUpdated":"10\/07\/22 13:21:12","AVG":"A82D96D824C12FA59936F5416FD5F14018220268"}},{"@attributes":{"Name":"Last Hope","Odds":"16\/1","OddsDecimal":"17.00","OddsAmerican":"1600","RaceOffOdds":"","SaddleCloth":"13","ID":"1266312598","LastUpdated":"10\/07\/22 08:30:06","AVG":"07F9036E26EB188C2C017FEE4A84FA6DA3820DD3"}},{"@attributes":{"Name":"Fontaine Del Rosso","Odds":"90\/1","OddsDecimal":"91.00","OddsAmerican":"9000","RaceOffOdds":"","SaddleCloth":"14","ID":"1266312675","LastUpdated":"10\/07\/22 13:08:10","AVG":"FE177CDB5E81E0642B03818EC75D35F83577B5B1"}},{"@attributes":{"Name":"Bonjour","Odds":"11\/2","OddsDecimal":"6.50","OddsAmerican":"550","RaceOffOdds":"","SaddleCloth":"15","ID":"1266312754","LastUpdated":"10\/07\/22 16:49:47","AVG":"BA87EA5D7CEB5B3731860B8C7BAFEA07CBF0118C"}},{"@attributes":{"Name":"Opicina","Odds":"70\/1","OddsDecimal":"71.00","OddsAmerican":"7000","RaceOffOdds":"","SaddleCloth":"17","ID":"1266312925","LastUpdated":"10\/07\/22 17:00:20","AVG":"420D511DB1346319545E33B8EECFC15C45A69525"}},{"@attributes":{"Name":"Franquin","Odds":"60\/1","OddsDecimal":"61.00","OddsAmerican":"6000","RaceOffOdds":"","SaddleCloth":"18","ID":"1266313004","LastUpdated":"10\/07\/22 17:02:52","AVG":"1504E0C557BA9B674A692334F662B5ADCD7EC839"}}]},{"@attributes":{"Name":"Cover Bet 4 places","ID":"20209","FID":"122024517"},"Participant":[{"@attributes":{"Name":"Eitilt","Odds":"9\/1","OddsDecimal":"10.00","OddsAmerican":"900","RaceOffOdds":"","SaddleCloth":"1","ID":"1266312007","LastUpdated":"10\/07\/22 13:28:29","AVG":"745069D514B5802FD5409ECECC5015358AD96C89"}},{"@attributes":{"Name":"Sizzling Sonata","Odds":"9\/20","OddsDecimal":"1.45","OddsAmerican":"-222","RaceOffOdds":"","SaddleCloth":"3","ID":"1266312056","LastUpdated":"10\/07\/22 13:28:29","AVG":"0AF6615100D257E83B124B7ECFDBBCCC2249AADA"}},{"@attributes":{"Name":"Almighty Will","Odds":"15\/2","OddsDecimal":"8.50","OddsAmerican":"750","RaceOffOdds":"","SaddleCloth":"4","ID":"1266312073","LastUpdated":"10\/07\/22 17:00:20","AVG":"6D063736E91112EDA0C8428842FA830A475BAAE1"}},{"@attributes":{"Name":"Rock Wave","Odds":"10\/1","OddsDecimal":"11.00","OddsAmerican":"1000","RaceOffOdds":"","SaddleCloth":"5","ID":"1266312094","LastUpdated":"10\/07\/22 13:28:29","AVG":"8578087919B962E6E718BF6AA962F99DA10A99A7"}},{"@attributes":{"Name":"Fast Melody","Odds":"11\/4","OddsDecimal":"3.75","OddsAmerican":"275","RaceOffOdds":"","SaddleCloth":"6","ID":"1266312123","LastUpdated":"10\/07\/22 17:02:52","AVG":"44CB71AF307195EB3195FA24E89C06292FC9BF56"}},{"@attributes":{"Name":"Ulanni","Odds":"11\/1","OddsDecimal":"12.00","OddsAmerican":"1100","RaceOffOdds":"","SaddleCloth":"7","ID":"1266312201","LastUpdated":"10\/07\/22 13:19:58","AVG":"D824CC71CED81D3FA17D280C2B7F94B500F7A41D"}},{"@attributes":{"Name":"My Divas","Odds":"12\/1","OddsDecimal":"13.00","OddsAmerican":"1200","RaceOffOdds":"","SaddleCloth":"9","ID":"1266312350","LastUpdated":"10\/07\/22 17:00:20","AVG":"EF3AEFEAF773F828C7D99FB8DB887DACF49874AE"}},{"@attributes":{"Name":"Rojean","Odds":"5\/4","OddsDecimal":"2.25","OddsAmerican":"125","RaceOffOdds":"","SaddleCloth":"10","ID":"1266312406","LastUpdated":"10\/07\/22 13:33:11","AVG":"1303E808FF0E80B3CE8B4ABACF47FFFC8FBD7406"}},{"@attributes":{"Name":"Annie's Comet","Odds":"12\/1","OddsDecimal":"13.00","OddsAmerican":"1200","RaceOffOdds":"","SaddleCloth":"11","ID":"1266312471","LastUpdated":"10\/07\/22 17:00:20","AVG":"B16B6D6221A655CD20834B56200943C7352A5F67"}},{"@attributes":{"Name":"Romanesco Fresco","Odds":"18\/1","OddsDecimal":"19.00","OddsAmerican":"1800","RaceOffOdds":"","SaddleCloth":"12","ID":"1266312549","LastUpdated":"10\/07\/22 13:21:12","AVG":"1CFE54B7E9702757BCA0FB277A8DCD59961145CF"}},{"@attributes":{"Name":"Last Hope","Odds":"14\/1","OddsDecimal":"15.00","OddsAmerican":"1400","RaceOffOdds":"","SaddleCloth":"13","ID":"1266312602","LastUpdated":"10\/07\/22 08:30:06","AVG":"D7221CF90A750EF67B924A19C55B73CA4A64E178"}},{"@attributes":{"Name":"Fontaine Del Rosso","Odds":"90\/1","OddsDecimal":"91.00","OddsAmerican":"9000","RaceOffOdds":"","SaddleCloth":"14","ID":"1266312680","LastUpdated":"10\/07\/22 13:08:10","AVG":"5AC3A1FC3669496282E20B28C8D95D6969CEF1B5"}},{"@attributes":{"Name":"Bonjour","Odds":"9\/2","OddsDecimal":"5.50","OddsAmerican":"450","RaceOffOdds":"","SaddleCloth":"15","ID":"1266312759","LastUpdated":"10\/07\/22 15:00:19","AVG":"F64C0C6B2383FF186373F41421393F8D7010369B"}},{"@attributes":{"Name":"Opicina","Odds":"70\/1","OddsDecimal":"71.00","OddsAmerican":"7000","RaceOffOdds":"","SaddleCloth":"17","ID":"1266312931","LastUpdated":"10\/07\/22 17:00:20","AVG":"436CF328257C8F95ACBFAD76A8E8D722095712CF"}},{"@attributes":{"Name":"Franquin","Odds":"60\/1","OddsDecimal":"61.00","OddsAmerican":"6000","RaceOffOdds":"","SaddleCloth":"18","ID":"1266313009","LastUpdated":"10\/07\/22 17:02:52","AVG":"61324F29BBA83462F274C335853EEC6C32841B53"}}]}]}}