{"@attributes":{"Name":"Horse Racing","PageTitle":"Filtered applied. EventID: 116630593","TimeStamp":"10\/07\/22 18:27:01"},"Event":{"@attributes":{"Name":"Stayers' Hurdle","ID":"116630593","OffTime":"16\/03\/23 15:30:00","EventComment":"","Going":"","RaceType":"","RaceDistance":"","PlaceCount":"3","PlaceOdds":"1\/5","PGID":"116630593"},"Market":{"@attributes":{"Name":"Win And Each Way","ID":"1744","FID":"116630593"},"Participant":[{"@attributes":{"Name":"Flooring Porter","Odds":"6\/1","OddsDecimal":"7.00","OddsAmerican":"600","RaceOffOdds":"","SaddleCloth":"0","ID":"773214878","LastUpdated":"09\/04\/22 15:45:38","AVG":"C64587AAFB3061DEE3C32BF6D977ED5F29E2E478"}},{"@attributes":{"Name":"Thyme Hill","Odds":"20\/1","OddsDecimal":"21.00","OddsAmerican":"2000","RaceOffOdds":"","SaddleCloth":"0","ID":"773214881","LastUpdated":"09\/04\/22 15:45:39","AVG":"05DCB1C0A3CA8E2802093281BA5A45CD33B3F257"}},{"@attributes":{"Name":"Klassical Dream","Odds":"12\/1","OddsDecimal":"13.00","OddsAmerican":"1200","RaceOffOdds":"","SaddleCloth":"0","ID":"773214882","LastUpdated":"23\/05\/22 15:11:08","AVG":"73375FF5D1E0A691A10AB7F7DF65C731C5818ED6"}},{"@attributes":{"Name":"Royal Kahala","Odds":"33\/1","OddsDecimal":"34.00","OddsAmerican":"3300","RaceOffOdds":"","SaddleCloth":"0","ID":"773214886","LastUpdated":"20\/03\/22 09:24:24","AVG":"B25AD76CAC06CBFE0F6A7FCCDCBA258D0C81B1DA"}},{"@attributes":{"Name":"Zanahiyr","Odds":"20\/1","OddsDecimal":"21.00","OddsAmerican":"2000","RaceOffOdds":"","SaddleCloth":"0","ID":"776929221","LastUpdated":"23\/05\/22 15:10:54","AVG":"10E6D7AF865B15F0BDE512D124742444BBCCB55A"}},{"@attributes":{"Name":"Vanillier","Odds":"40\/1","OddsDecimal":"41.00","OddsAmerican":"4000","RaceOffOdds":"","SaddleCloth":"0","ID":"781660532","LastUpdated":"28\/04\/22 17:32:52","AVG":"779819A5B21FDFFA63F7AC3F1A3B8538CF146722"}},{"@attributes":{"Name":"Sporting John","Odds":"33\/1","OddsDecimal":"34.00","OddsAmerican":"3300","RaceOffOdds":"","SaddleCloth":"0","ID":"781660538","LastUpdated":"28\/03\/22 12:38:26","AVG":"6803EC8067786397387D13DF0C1D9B42BA067C85"}},{"@attributes":{"Name":"Bob Olinger","Odds":"20\/1","OddsDecimal":"21.00","OddsAmerican":"2000","RaceOffOdds":"","SaddleCloth":"0","ID":"782383447","LastUpdated":"26\/04\/22 18:45:22","AVG":"0E82A1DBA7EC8F9969F6962ECD4DE0DF7096A126"}},{"@attributes":{"Name":"Buzz","Odds":"12\/1","OddsDecimal":"13.00","OddsAmerican":"1200","RaceOffOdds":"","SaddleCloth":"0","ID":"785732054","LastUpdated":"20\/03\/22 09:22:59","AVG":"E34835F92B82BF422601EE31CE6198EBD49C3940"}},{"@attributes":{"Name":"Love Envoi","Odds":"20\/1","OddsDecimal":"21.00","OddsAmerican":"2000","RaceOffOdds":"","SaddleCloth":"0","ID":"785732065","LastUpdated":"17\/04\/22 15:22:28","AVG":"DFBA809D58576C462A29AE1DC989CC1C33A7C626"}},{"@attributes":{"Name":"The Nice Guy","Odds":"10\/1","OddsDecimal":"11.00","OddsAmerican":"1000","RaceOffOdds":"","SaddleCloth":"0","ID":"785732073","LastUpdated":"27\/04\/22 17:29:15","AVG":"371C5F832ABE62F5A2E488A269D4563906D6B23B"}},{"@attributes":{"Name":"Blazing Khal","Odds":"16\/1","OddsDecimal":"17.00","OddsAmerican":"1600","RaceOffOdds":"","SaddleCloth":"0","ID":"785732088","LastUpdated":"20\/03\/22 09:23:09","AVG":"6283576B29C91DDEC06D7FEA0DADE0242B977E43"}},{"@attributes":{"Name":"Champ","Odds":"25\/1","OddsDecimal":"26.00","OddsAmerican":"2500","RaceOffOdds":"","SaddleCloth":"0","ID":"785732112","LastUpdated":"09\/04\/22 15:45:40","AVG":"BDFF79E7446F8DA2DCFD267211D2F9C81650A626"}},{"@attributes":{"Name":"Three Stripe Life","Odds":"16\/1","OddsDecimal":"17.00","OddsAmerican":"1600","RaceOffOdds":"","SaddleCloth":"0","ID":"785732141","LastUpdated":"29\/04\/22 18:09:02","AVG":"FB7A090322474CAE1FA57BE75529514AC160F96C"}},{"@attributes":{"Name":"Minella Crooner","Odds":"40\/1","OddsDecimal":"41.00","OddsAmerican":"4000","RaceOffOdds":"","SaddleCloth":"0","ID":"785732169","LastUpdated":"27\/04\/22 17:29:29","AVG":"C3E98AF62E83C9388C12CFD45DE4E6AA504B5F80"}},{"@attributes":{"Name":"Kilcruit","Odds":"33\/1","OddsDecimal":"34.00","OddsAmerican":"3300","RaceOffOdds":"","SaddleCloth":"0","ID":"785732200","LastUpdated":"29\/04\/22 18:08:54","AVG":"BEEB39D215733999988F3F7F65CBC405EDAB30B0"}},{"@attributes":{"Name":"Third Wind","Odds":"33\/1","OddsDecimal":"34.00","OddsAmerican":"3300","RaceOffOdds":"","SaddleCloth":"0","ID":"785732228","LastUpdated":"20\/03\/22 09:23:24","AVG":"FA278E45AC79E460FAB38008FB7CA86E43AFB2B2"}},{"@attributes":{"Name":"Minella Cocooner","Odds":"16\/1","OddsDecimal":"17.00","OddsAmerican":"1600","RaceOffOdds":"","SaddleCloth":"0","ID":"785732237","LastUpdated":"27\/04\/22 17:29:27","AVG":"68F486F8AFD9D73A36CA1E5DFE75D93564544A87"}},{"@attributes":{"Name":"Paisley Park","Odds":"33\/1","OddsDecimal":"34.00","OddsAmerican":"3300","RaceOffOdds":"","SaddleCloth":"0","ID":"785732239","LastUpdated":"28\/04\/22 17:32:56","AVG":"E135D1857AB68DBE83800407E71F6A5F733B30AB"}},{"@attributes":{"Name":"Hillcrest","Odds":"50\/1","OddsDecimal":"51.00","OddsAmerican":"5000","RaceOffOdds":"","SaddleCloth":"0","ID":"785732241","LastUpdated":"21\/03\/22 15:41:08","AVG":"AC7CFD71BDEF0C9B82178E68609D21A926126C3C"}},{"@attributes":{"Name":"The Big Breakaway","Odds":"50\/1","OddsDecimal":"51.00","OddsAmerican":"5000","RaceOffOdds":"","SaddleCloth":"0","ID":"785732257","LastUpdated":"20\/03\/22 09:23:33","AVG":"073955BBE09CC3D286C660E4ACC936D1EB17C27D"}},{"@attributes":{"Name":"Chantry House","Odds":"50\/1","OddsDecimal":"51.00","OddsAmerican":"5000","RaceOffOdds":"","SaddleCloth":"0","ID":"785732260","LastUpdated":"20\/03\/22 09:23:35","AVG":"DE27CA88F2351C4C6C9D2FCC171FBB33BF8B1102"}},{"@attributes":{"Name":"Alaphilippe","Odds":"33\/1","OddsDecimal":"34.00","OddsAmerican":"3300","RaceOffOdds":"","SaddleCloth":"0","ID":"789194204","LastUpdated":"21\/03\/22 08:30:47","AVG":"0E38C776BA0EA9C58F48A69606453E3A2F7F9258"}},{"@attributes":{"Name":"Thedevilscoachman","Odds":"33\/1","OddsDecimal":"34.00","OddsAmerican":"3300","RaceOffOdds":"","SaddleCloth":"0","ID":"793512984","LastUpdated":"22\/03\/22 10:17:49","AVG":"7CC4945669BA787A1B053BEFE2B7142CD12691C0"}},{"@attributes":{"Name":"Mrs Milner","Odds":"50\/1","OddsDecimal":"51.00","OddsAmerican":"5000","RaceOffOdds":"","SaddleCloth":"0","ID":"797310073","LastUpdated":"30\/04\/22 16:00:02","AVG":"236578E5B640CEFCF02BF6AB903DF76FBD6EAE22"}},{"@attributes":{"Name":"Epatante","Odds":"12\/1","OddsDecimal":"13.00","OddsAmerican":"1200","RaceOffOdds":"","SaddleCloth":"0","ID":"866441373","LastUpdated":"30\/04\/22 16:00:06","AVG":"0DB69CB5D1B2F3C447659B0E6EF85CC0C117E1AD"}},{"@attributes":{"Name":"Langer Dan","Odds":"25\/1","OddsDecimal":"26.00","OddsAmerican":"2500","RaceOffOdds":"","SaddleCloth":"0","ID":"878766707","LastUpdated":"10\/04\/22 08:31:36","AVG":"0CBB202EE5970E3032BAD6BF378380C9E73168AF"}},{"@attributes":{"Name":"Jon Snow","Odds":"33\/1","OddsDecimal":"34.00","OddsAmerican":"3300","RaceOffOdds":"","SaddleCloth":"0","ID":"911106358","LastUpdated":"05\/06\/22 15:53:39","AVG":"B96B42006DE5FF7E69BF4F4D305A7954AE1767A2"}},{"@attributes":{"Name":"Might I","Odds":"40\/1","OddsDecimal":"41.00","OddsAmerican":"4000","RaceOffOdds":"","SaddleCloth":"0","ID":"943995088","LastUpdated":"24\/04\/22 09:16:23","AVG":"007392E1CA11592FAD7D5D5B866A24C1F70F31F8"}},{"@attributes":{"Name":"Fusil Raffles","Odds":"40\/1","OddsDecimal":"41.00","OddsAmerican":"4000","RaceOffOdds":"","SaddleCloth":"0","ID":"943995106","LastUpdated":"24\/04\/22 09:16:23","AVG":"F855CEC0DE55F03D6D159804331FDCD3EB727C2C"}},{"@attributes":{"Name":"State Man","Odds":"10\/1","OddsDecimal":"11.00","OddsAmerican":"1000","RaceOffOdds":"","SaddleCloth":"0","ID":"966395850","LastUpdated":"29\/04\/22 18:09:01","AVG":"EFA47671D66018E0D736B8B82D4ABD14FAE35B15"}},{"@attributes":{"Name":"Marie's Rock","Odds":"16\/1","OddsDecimal":"17.00","OddsAmerican":"1600","RaceOffOdds":"","SaddleCloth":"0","ID":"977524853","LastUpdated":"01\/05\/22 14:08:24","AVG":"C1C6B3EE481231814FD789A7671DE5A0596D9CAB"}}]}}}